Metadata-Version: 2.1
Name: codeclarity
Version: 0.1
Summary: An embedding tool for all state of the art code language models
Home-page: https://github.com/DocumaticAI/CodeClarity
Author: Charlie Masters
Author-email: cm2435@bath.ac.uk
License: MIT
Keywords: sentence,embedding,code,search,contrastive,nlp,deep_learning,semantic
